gitlab_tags_to_pip_index.py
gitlab_tags_to_pip_index-1.9.dist-info/LICENSE
gitlab_tags_to_pip_index-1.9.dist-info/METADATA
gitlab_tags_to_pip_index-1.9.dist-info/WHEEL
gitlab_tags_to_pip_index-1.9.dist-info/entry_points.txt
gitlab_tags_to_pip_index-1.9.dist-info/top_level.txt
gitlab_tags_to_pip_index-1.9.dist-info/RECORD
