Metadata-Version: 2.1
Name: gitlab-tags-to-pip-index
Version: 1.9
Summary: Utility for use in gitlab ci to create python repo web pages from project tags
Home-page: https://gitlab.com/alelec/gitlab-tags-to-pip-index
Author: Andrew Leech
Author-email: andrew@alelec.net
License: MIT
Platform: UNKNOWN
Requires-Dist: requests
Requires-Dist: mako
